iolConn/__init__.py
iolConn/iolConn.py
iolConn/common/__init__.py
iolConn/common/exceptions.py
iolConn-0.4.2.dist-info/LICENSE
iolConn-0.4.2.dist-info/METADATA
iolConn-0.4.2.dist-info/WHEEL
iolConn-0.4.2.dist-info/top_level.txt
iolConn-0.4.2.dist-info/RECORD
