Metadata-Version: 2.1
Name: iolConn
Version: 0.4.2
Summary: Conector python para API de InvertirOnline.
Home-page: https://github.com/diegolpedro/iolConn
Author: Pedro Diego
Author-email: diegolpedro@gmail.com
License: file : LICENSE
Keywords: iol,markets
Classifier: Programming Language :: Python :: 3
Requires-Python: >=3.7
License-File: LICENSE
Requires-Dist: urllib3 ==1.26.6
Requires-Dist: requests ==2.31.0
